pwdkek_python/__init__.py
pwdkek_python/__main__.py
pwdkek_python/builtin_datasets.py
pwdkek_python/complexity_estimator.py
pwdkek_python/prepare_dataset.py
pwdkek_python-0.1.2.dist-info/METADATA
pwdkek_python-0.1.2.dist-info/WHEEL
pwdkek_python-0.1.2.dist-info/RECORD
