Metadata-Version: 2.1
Name: pwdkek-python
Version: 0.1.2
Summary: 
Author: Vitaly Mahonin
Requires-Python: >=3.11,<4.0
Classifier: Programming Language :: Python :: 3
Classifier: Programming Language :: Python :: 3.11
Classifier: Programming Language :: Python :: 3.12
